py2pack/__init__.py
py2pack/requires.py
py2pack/spdx_license_map.json
py2pack/utils.py
py2pack/version.py
py2pack/templates/fedora.spec
py2pack/templates/mageia.spec
py2pack/templates/opensuse-legacy.spec
py2pack/templates/opensuse.dsc
py2pack/templates/opensuse.spec
py2pack-0.9.1.dist-info/METADATA
py2pack-0.9.1.dist-info/WHEEL
py2pack-0.9.1.dist-info/entry_points.txt
py2pack-0.9.1.dist-info/licenses/LICENSE
py2pack-0.9.1.dist-info/RECORD
