Metadata-Version: 2.4
Name: py2pack
Version: 0.9.1
Summary: Generate distribution packages from PyPI
Project-URL: homepage, http://github.com/openSUSE/py2pack
Author-email: Sascha Peilicke <sascha@peilicke.de>, Thomas Bechtold <thomasbechtold@jpberlin.de>
Maintainer-email: Paolo Perego <paolo@codiceinsicuro.it>
License: 
License-File: LICENSE
Classifier: Development Status :: 4 - Beta
Classifier: Environment :: Console
Classifier: Intended Audience :: Developers
Classifier: Intended Audience :: End Users/Desktop
Classifier: Intended Audience :: System Administrators
Classifier: License :: OSI Approved :: Apache Software License
Classifier: Operating System :: POSIX
Classifier: Programming Language :: Python :: 3
Classifier: Topic :: Software Development :: Code Generators
Classifier: Topic :: Software Development :: Pre-processors
Requires-Python: >=3.6
Requires-Dist: backports-entry-points-selectable
Requires-Dist: build
Requires-Dist: jinja2
Requires-Dist: metaextract
Requires-Dist: packaging
Requires-Dist: platformdirs
Requires-Dist: pypi-search
Requires-Dist: requests
Requires-Dist: setuptools
Requires-Dist: tomli; python_version < '3.11'
